[{"uuid":"f8d0fd6a-6204-4c85-8abb-75c7007b1efc","type":"POLICE","subtype":"POLICE_VISIBLE","location":{"x":18.653597,"y":50.062137},"pubMillis":1718458340000},{"uuid":"5dff6846-cd42-483d-99de-d9107e160d68","type":"POLICE","subtype":"POLICE_HIDING","location":{"x":19.13108,"y":50.083841},"pubMillis":1718458356000},{"uuid":"8cf056b1-94dd-41e7-99b8-3bf040d48d89","type":"POLICE","subtype":"","location":{"x":19.493104,"y":50.063509},"pubMillis":1718458183000},{"uuid":"aa9b0af9-04d2-4113-aab8-258c878a7647","type":"POLICE","subtype":"","location":{"x":19.493465,"y":50.149236},"pubMillis":1718457106000},{"uuid":"242e5723-3c74-425f-aef1-a7be8758daea","type":"POLICE","subtype":"","location":{"x":18.70303,"y":50.194475},"pubMillis":1718458600000},{"uuid":"818ece4d-0ea4-4cc0-9e54-31a834716754","type":"POLICE","subtype":"POLICE_HIDING","location":{"x":19.443937,"y":50.152425},"pubMillis":1718457195000},{"uuid":"87efa072-d880-4482-b55a-cbb16d48ab12","type":"POLICE","subtype":"","location":{"x":18.796301,"y":50.257665},"pubMillis":1718458803000},{"uuid":"3e51c21e-4158-402a-af25-4cb6167bc5d1","type":"POLICE","subtype":"","location":{"x":18.965653,"y":50.255854},"pubMillis":1718457997000},{"uuid":"e68e8595-ca50-4782-a873-e3a23eb04540","type":"POLICE","subtype":"","location":{"x":18.967956,"y":50.294214},"pubMillis":1718456985000},{"uuid":"45758764-4aab-4a74-9a05-45995f6628ae","type":"POLICE","subtype":"","location":{"x":19.077669,"y":50.267856},"pubMillis":1718457157000},{"uuid":"1e9daed0-d8e2-4328-81a3-e3c5ad57e61c","type":"POLICE","subtype":"","location":{"x":19.147597,"y":50.26774},"pubMillis":1718456269000},{"uuid":"4d00e24a-34a8-48bf-b655-d89d9e7fbe43","type":"POLICE","subtype":"","location":{"x":18.950635,"y":50.303669},"pubMillis":1718456169000},{"uuid":"b8c7e231-fc72-40ea-bfba-9dce9bde0509","type":"POLICE","subtype":"POLICE_HIDING","location":{"x":19.130874,"y":50.083851},"pubMillis":1718459234000},{"uuid":"487d2064-b1de-49ae-b6fd-96bc73dbd447","type":"POLICE","subtype":"POLICE_HIDING","location":{"x":18.684569,"y":50.281966},"pubMillis":1718459641000},{"uuid":"611680b3-496f-4027-93fd-64262feb07ee","type":"POLICE","subtype":"","location":{"x":18.534505,"y":50.343623},"pubMillis":1718460009000},{"uuid":"43ff8de5-c8b8-4596-8375-4a869dd5916d","type":"POLICE","subtype":"POLICE_HIDING","location":{"x":19.157682,"y":50.300444},"pubMillis":1718460356000},{"uuid":"cdd93bd6-f0c0-4ba8-83f2-5c8c92298ec2","type":"POLICE","subtype":"","location":{"x":19.158972,"y":50.300404},"pubMillis":1718460353000},{"uuid":"195074f1-2a4e-4757-8278-2cb2f1c4c99d","type":"POLICE","subtype":"","location":{"x":19.02488,"y":50.244724},"pubMillis":1718460526000},{"uuid":"adbf6667-2720-4495-b3a9-a28e86ce255b","type":"POLICE","subtype":"POLICE_HIDING","location":{"x":19.022654,"y":50.319574},"pubMillis":1718460627000},{"uuid":"1750c824-7c29-47ec-9261-10eafcbdc48f","type":"POLICE","subtype":"POLICE_HIDING","location":{"x":18.939682,"y":50.33333},"pubMillis":1718460770000},{"uuid":"873cc6a9-bbee-4b3b-bc0e-6edb6abaf709","type":"POLICE","subtype":"","location":{"x":19.253369,"y":50.340237},"pubMillis":1718461581000},{"uuid":"9d35fee6-b479-44e8-b1fb-d6e3cddeea71","type":"POLICE","subtype":"","location":{"x":19.163,"y":50.379583},"pubMillis":1718461589000},{"uuid":"edd117f4-003d-4e4f-ae19-5c61ff1991be","type":"POLICE","subtype":"","location":{"x":19.022592,"y":50.32022},"pubMillis":1718461689000},{"uuid":"ada8e61c-31fa-47f9-b643-a55dfad5e1b6","type":"POLICE","subtype":"","location":{"x":19.257918,"y":50.349782},"pubMillis":1718461745000},{"uuid":"44526573-9070-4029-960a-fd0b4241ed5d","type":"POLICE","subtype":"","location":{"x":19.006521,"y":50.103017},"pubMillis":1718462677000},{"uuid":"d96a5153-253d-45e7-b1a9-96a62d5ada7d","type":"POLICE","subtype":"","location":{"x":19.024624,"y":50.244248},"pubMillis":1718462575000},{"uuid":"f5debe5e-f303-41a8-ad83-d84de66a73f9","type":"POLICE","subtype":"","location":{"x":18.796361,"y":50.257825},"pubMillis":1718462780000},{"uuid":"afd5d67d-139e-4c37-bc24-1e5e7158bd83","type":"POLICE","subtype":"POLICE_HIDING","location":{"x":18.862215,"y":50.277688},"pubMillis":1718464525000},{"uuid":"78df4dca-0230-4a22-bfe5-899b42ab77d8","type":"POLICE","subtype":"","location":{"x":19.074836,"y":50.317504},"pubMillis":1718464607000},{"uuid":"f7f21604-fa5f-4412-9c8e-4b0f4b9ea01d","type":"POLICE","subtype":"POLICE_HIDING","location":{"x":18.796907,"y":50.260498},"pubMillis":1718465234000},{"uuid":"ddd93bbd-7911-4161-8e13-a6a25d6e9d1c","type":"POLICE","subtype":"POLICE_HIDING","location":{"x":18.971094,"y":50.299968},"pubMillis":1718465102000},{"uuid":"e586fe8c-d202-481c-9053-874bb0594acc","type":"POLICE","subtype":"","location":{"x":19.33609,"y":50.109038},"pubMillis":1718465304000},{"uuid":"b3cba3d0-d93f-4a55-88ae-d8064fe4ec23","type":"POLICE","subtype":"","location":{"x":19.063692,"y":50.232859},"pubMillis":1718465355000},{"uuid":"e5fb3094-9cf1-4725-8e36-dbfc691e1207","type":"POLICE","subtype":"POLICE_HIDING","location":{"x":19.202219,"y":50.420158},"pubMillis":1718465510000},{"uuid":"4618e6a4-f3e0-4772-b0ab-74a1d9b8c523","type":"POLICE","subtype":"","location":{"x":18.673217,"y":50.03197},"pubMillis":1718465570000},{"uuid":"6b09bd26-c031-42e8-b79e-c8e641e109b6","type":"POLICE","subtype":"","location":{"x":19.191556,"y":50.065054},"pubMillis":1718465879000},{"uuid":"c4f5053f-b935-4c68-9bec-e8c0f3e44950","type":"POLICE","subtype":"","location":{"x":19.267629,"y":50.354948},"pubMillis":1718466028000},{"uuid":"8be93ef7-00b4-4f65-a3b1-a6343e0bb339","type":"POLICE","subtype":"","location":{"x":18.936754,"y":50.358477},"pubMillis":1718466415000},{"uuid":"f420c1e1-036f-4991-a9eb-26b12ead15de","type":"POLICE","subtype":"","location":{"x":19.003891,"y":50.127015},"pubMillis":1718466583000},{"uuid":"06066289-248b-4707-9dbc-6be05af9c9a9","type":"POLICE","subtype":"","location":{"x":18.68448,"y":50.282006},"pubMillis":1718466994000},{"uuid":"d0010147-1147-4387-a704-9e9c59a908c2","type":"POLICE","subtype":"","location":{"x":18.981933,"y":50.321182},"pubMillis":1718467074000},{"uuid":"ef9045a1-aa49-4a48-bea3-394b83ccf92f","type":"POLICE","subtype":"","location":{"x":19.123993,"y":50.286665},"pubMillis":1718467332000},{"uuid":"6f10e7d4-a17c-44e5-a2c6-699cc291e527","type":"POLICE","subtype":"","location":{"x":19.125096,"y":50.286481},"pubMillis":1718467354000},{"uuid":"036295d5-3958-418b-a6ee-796109616e7a","type":"POLICE","subtype":"","location":{"x":18.976175,"y":50.338938},"pubMillis":1718467672000},{"uuid":"21970e56-c347-43bf-8b86-eaba34d62813","type":"POLICE","subtype":"","location":{"x":18.852907,"y":50.207588},"pubMillis":1718468106000},{"uuid":"8e958a26-dc3d-454b-b5e1-cd5cec8fe1c8","type":"POLICE","subtype":"","location":{"x":18.881002,"y":50.299187},"pubMillis":1718468243000},{"uuid":"883319f7-1502-4ed3-9bb9-fa5b04ba82ea","type":"POLICE","subtype":"POLICE_HIDING","location":{"x":19.174384,"y":50.076519},"pubMillis":1718468644000},{"uuid":"b18491c7-9ddf-42b9-98a3-dae984a61a46","type":"POLICE","subtype":"","location":{"x":19.060375,"y":50.503141},"pubMillis":1718468932000},{"uuid":"ccc0509d-df40-4a45-93ac-05c23d7121e5","type":"POLICE","subtype":"","location":{"x":19.174301,"y":50.281075},"pubMillis":1718469351000},{"uuid":"9e411b97-08f4-4e58-aec9-220150684c97","type":"POLICE","subtype":"POLICE_HIDING","location":{"x":19.129972,"y":50.083893},"pubMillis":1718469518000},{"uuid":"853db9a1-e488-4c57-a19b-a715f17a9527","type":"POLICE","subtype":"","location":{"x":18.596136,"y":50.132311},"pubMillis":1718469521000},{"uuid":"36030c7d-e4a6-4fe5-a7b9-abd41680544e","type":"POLICE","subtype":"","location":{"x":18.943963,"y":50.374233},"pubMillis":1718469624000},{"uuid":"164f52dc-a801-4404-b81d-6405bb6680ae","type":"POLICE","subtype":"","location":{"x":18.991074,"y":50.224772},"pubMillis":1718469748000},{"uuid":"e01c35d0-0f35-4c18-8329-5644f63c0c2b","type":"POLICE","subtype":"POLICE_HIDING","location":{"x":19.471618,"y":50.387723},"pubMillis":1718470155000},{"uuid":"f0945974-6273-4776-81b3-634e8ac5b7e5","type":"POLICE","subtype":"","location":{"x":19.272134,"y":50.22867},"pubMillis":1718471081000},{"uuid":"2620cf1e-0b62-47ca-ad39-ecfd18485061","type":"POLICE","subtype":"POLICE_HIDING","location":{"x":19.110032,"y":50.334211},"pubMillis":1718471145000},{"uuid":"7b24ea0f-ee5b-4076-b55f-ab9cadeba75e","type":"POLICE","subtype":"","location":{"x":19.238894,"y":50.34176},"pubMillis":1718471967000},{"uuid":"2f33900c-8bff-4cb2-ab6d-a64bc186675e","type":"POLICE","subtype":"POLICE_HIDING","location":{"x":19.011853,"y":50.265414},"pubMillis":1718472430000},{"uuid":"3faa2e62-49fb-4ef4-9573-584a36d71b4c","type":"POLICE","subtype":"","location":{"x":18.899897,"y":50.295868},"pubMillis":1718472749000},{"uuid":"c3ae116b-0079-497e-a3b7-f7fa9761d630","type":"POLICE","subtype":"","location":{"x":18.739626,"y":50.251744},"pubMillis":1718473283000},{"uuid":"575761f9-d3e3-4bfe-b5b2-e2b3dd8ba282","type":"POLICE","subtype":"POLICE_HIDING","location":{"x":18.946528,"y":50.317427},"pubMillis":1718473914000},{"uuid":"ee827de0-7ee0-4823-95c1-e2ec7cb15c9b","type":"POLICE","subtype":"POLICE_HIDING","location":{"x":19.158673,"y":50.300326},"pubMillis":1718474062000},{"uuid":"1a8be67f-d299-4625-831e-547d8493d468","type":"POLICE","subtype":"","location":{"x":19.468694,"y":50.068236},"pubMillis":1718474533000},{"uuid":"d14f575e-9bf2-4953-b96a-8b7e45baedc7","type":"POLICE","subtype":"","location":{"x":18.509089,"y":50.252773},"pubMillis":1718474894000},{"uuid":"26f7b3f5-8f42-412b-aa50-f5c90a283a04","type":"POLICE","subtype":"","location":{"x":19.016428,"y":50.329679},"pubMillis":1718475065000},{"uuid":"fae4e28f-4e0d-43fa-a7b5-30a1e5ead8d9","type":"POLICE","subtype":"POLICE_HIDING","location":{"x":19.016616,"y":50.329643},"pubMillis":1718475559000},{"uuid":"0005bebe-996b-4d59-b2f7-23d8c6defbf1","type":"POLICE","subtype":"","location":{"x":19.190127,"y":50.398119},"pubMillis":1718475931000},{"uuid":"dc6ad407-d405-4f91-b731-6fd65da3eea7","type":"POLICE","subtype":"","location":{"x":18.93992,"y":50.253691},"pubMillis":1718476764000},{"uuid":"05ef2be4-de52-4efe-8417-de40556f8f31","type":"POLICE","subtype":"POLICE_HIDING","location":{"x":18.946187,"y":50.318091},"pubMillis":1718476977000},{"uuid":"7ffbcf7d-6467-4f02-b98e-0bd1a7090731","type":"POLICE","subtype":"POLICE_HIDING","location":{"x":18.94643,"y":50.317697},"pubMillis":1718479731000},{"uuid":"47362a4c-8417-4b0a-98d0-7d6a21e6d457","type":"POLICE","subtype":"","location":{"x":18.968154,"y":50.293085},"pubMillis":1718482349000},{"uuid":"2c81f39f-c88a-4d19-91e0-bf03f9bfc209","type":"POLICE","subtype":"POLICE_HIDING","location":{"x":18.914234,"y":50.183655},"pubMillis":1718482984000},{"uuid":"f3e3d128-df26-48e2-8c79-799619e2fcd6","type":"POLICE","subtype":"","location":{"x":18.910021,"y":50.180131},"pubMillis":1718483045000},{"uuid":"9735fe4e-edb3-4cb7-8bad-e6fc7c0112bf","type":"POLICE","subtype":"","location":{"x":18.955479,"y":50.278347},"pubMillis":1718483002000},{"uuid":"9ab0a0c8-a1ca-4d14-a836-970b7e35e9d3","type":"POLICE","subtype":"POLICE_HIDING","location":{"x":18.960797,"y":50.275102},"pubMillis":1718483228000},{"uuid":"af95e414-2641-4579-8685-2bea08a8e834","type":"POLICE","subtype":"","location":{"x":18.93669,"y":50.357729},"pubMillis":1718483831000},{"uuid":"7c6cc12d-0afb-406b-9877-45e6589cec81","type":"POLICE","subtype":"","location":{"x":18.986908,"y":50.275212},"pubMillis":1718484571000},{"uuid":"1592086a-b516-49b7-a570-16f6fd72cfee","type":"POLICE","subtype":"POLICE_HIDING","location":{"x":18.987032,"y":50.275131},"pubMillis":1718484528000},{"uuid":"9378ec5c-d652-4251-a84e-e7bead9db808","type":"POLICE","subtype":"","location":{"x":18.96798,"y":50.294083},"pubMillis":1718484995000},{"uuid":"4b5d9887-acee-4f70-a2d1-9cf70545766b","type":"POLICE","subtype":"","location":{"x":19.110735,"y":50.28006},"pubMillis":1718486936000},{"uuid":"40a3a88a-ba24-4825-9c66-ebe8928b8f12","type":"POLICE","subtype":"POLICE_HIDING","location":{"x":19.017638,"y":50.171713},"pubMillis":1718487315000},{"uuid":"af02e9c0-1a52-4b88-8a95-0b622a8cb946","type":"POLICE","subtype":"","location":{"x":18.858239,"y":50.258111},"pubMillis":1718487434000},{"uuid":"b85c8ad6-7579-4ff4-b831-4c5c76e76bc2","type":"POLICE","subtype":"","location":{"x":18.947619,"y":50.282638},"pubMillis":1718487709000},{"uuid":"0c3dd226-cab4-4896-a0b7-be1afb8931d1","type":"POLICE","subtype":"","location":{"x":18.89406,"y":50.371146},"pubMillis":1718487958000},{"uuid":"c084f9f7-a867-4e8c-be8a-e60db5a47cfe","type":"POLICE","subtype":"","location":{"x":18.974599,"y":50.368925},"pubMillis":1718488742000},{"uuid":"be12fc49-0959-4e01-80fb-eb667b8e2e16","type":"POLICE","subtype":"","location":{"x":18.868156,"y":50.35754},"pubMillis":1718489371000},{"uuid":"6ae5ea68-812b-4e30-b41f-3e6f956f628f","type":"POLICE","subtype":"","location":{"x":19.124063,"y":50.276784},"pubMillis":1718489856000},{"uuid":"607063ef-f614-4e5f-b4fe-613faf672614","type":"POLICE","subtype":"","location":{"x":18.950727,"y":50.289252},"pubMillis":1718490078000},{"uuid":"3b1a13c6-510c-49ca-b8c3-2cae4e1efed1","type":"POLICE","subtype":"","location":{"x":19.170831,"y":50.078644},"pubMillis":1718492886000},{"uuid":"9180d9f9-e5e1-4b2d-9e29-54014f95da76","type":"POLICE","subtype":"POLICE_HIDING","location":{"x":18.920489,"y":50.306292},"pubMillis":1718494911000},{"uuid":"3d616423-210f-4ec4-bcbf-1c5cd02f5d91","type":"POLICE","subtype":"POLICE_HIDING","location":{"x":18.94678,"y":50.342207},"pubMillis":1718499306000},{"uuid":"7a02804f-f0d8-4f74-95b2-b575483e0ed2","type":"POLICE","subtype":"","location":{"x":18.945332,"y":50.391139},"pubMillis":1718499517000},{"uuid":"483050f0-8ae6-4655-aaee-cc39d0e5aa8f","type":"POLICE","subtype":"","location":{"x":18.991015,"y":50.269764},"pubMillis":1718500051000},{"uuid":"b9aabe77-486a-48e1-9e1f-0d3e4f76f3b2","type":"POLICE","subtype":"","location":{"x":19.12266,"y":50.247823},"pubMillis":1718501394000},{"uuid":"9b3cb00a-b106-4ad0-b58f-b8ac54290e99","type":"POLICE","subtype":"POLICE_HIDING","location":{"x":18.884218,"y":50.306179},"pubMillis":1718512975000},{"uuid":"3449408f-e6a8-4c0d-8d94-419e9cb17209","type":"POLICE","subtype":"POLICE_HIDING","location":{"x":19.440457,"y":50.144762},"pubMillis":1718514009000},{"uuid":"98bd48ba-8d16-4861-8c21-b3d7d3443e46","type":"POLICE","subtype":"POLICE_HIDING","location":{"x":18.995975,"y":50.141499},"pubMillis":1718514724000},{"uuid":"c8d12299-7d34-4b72-a3e7-7969e1acc69b","type":"POLICE","subtype":"","location":{"x":19.093,"y":50.252625},"pubMillis":1718515237000},{"uuid":"808981d9-f9d8-4bb2-a19e-52cf88b126b0","type":"POLICE","subtype":"","location":{"x":18.893721,"y":50.374434},"pubMillis":1718515579000},{"uuid":"a87123cc-6cbb-4ec2-9659-1a792a0137fb","type":"POLICE","subtype":"","location":{"x":18.96389,"y":50.289932},"pubMillis":1718516161000},{"uuid":"f87dbaa5-9a36-4121-a3ca-d23648180622","type":"POLICE","subtype":"","location":{"x":18.965202,"y":50.289067},"pubMillis":1718517070000},{"uuid":"d3ae20aa-ad36-4a5f-95da-936a5c1f2b9e","type":"POLICE","subtype":"","location":{"x":18.811996,"y":50.439937},"pubMillis":1718517632000},{"uuid":"22c51010-4269-46c3-8890-0b0c43868385","type":"POLICE","subtype":"","location":{"x":19.482521,"y":50.482937},"pubMillis":1718518061000},{"uuid":"bc2baced-340f-41bf-b0f1-ca130577a972","type":"POLICE","subtype":"","location":{"x":19.094085,"y":50.25227},"pubMillis":1718518639000},{"uuid":"fd4abc75-95be-4dbb-bdd9-ac237762371e","type":"POLICE","subtype":"","location":{"x":19.135388,"y":50.256858},"pubMillis":1718518963000},{"uuid":"65cc5826-1e58-4c70-80a1-75b2d78f1a31","type":"POLICE","subtype":"","location":{"x":19.006254,"y":50.090717},"pubMillis":1718520599000},{"uuid":"e9bca59e-22c7-4e23-90d7-91439c7d1ce2","type":"POLICE","subtype":"","location":{"x":18.730688,"y":50.268338},"pubMillis":1718521637000},{"uuid":"b4471ea2-31bc-465f-81bf-6adca7541dba","type":"POLICE","subtype":"","location":{"x":19.210184,"y":50.03189},"pubMillis":1718522469000},{"uuid":"5b607fd9-217f-4988-8df6-17af5da4f3d7","type":"POLICE","subtype":"POLICE_HIDING","location":{"x":19.090776,"y":50.253503},"pubMillis":1718523488000},{"uuid":"0f65aaef-21b0-493b-b55c-95932e52d56b","type":"POLICE","subtype":"POLICE_HIDING","location":{"x":19.09194,"y":50.253347},"pubMillis":1718523929000},{"uuid":"43775ca8-fd1d-467e-88c5-fa557838cc01","type":"POLICE","subtype":"","location":{"x":19.138916,"y":50.273395},"pubMillis":1718524128000},{"uuid":"4d10a843-6483-4e2c-8e5c-29f72bdc5403","type":"POLICE","subtype":"POLICE_HIDING","location":{"x":19.070195,"y":50.258987},"pubMillis":1718525074000},{"uuid":"02257cc0-5dee-4b78-b702-21995c68d8ac","type":"POLICE","subtype":"","location":{"x":19.092869,"y":50.253149},"pubMillis":1718526006000},{"uuid":"3efd3830-d636-4507-adad-af2976493695","type":"POLICE","subtype":"","location":{"x":18.936995,"y":50.359147},"pubMillis":1718526014000},{"uuid":"75794c27-3c93-464e-868f-f30214125f1e","type":"POLICE","subtype":"","location":{"x":19.139806,"y":50.273409},"pubMillis":1718527002000},{"uuid":"9b5eb8fb-5310-48d5-91ca-76b11caaa7ee","type":"POLICE","subtype":"POLICE_HIDING","location":{"x":19.043017,"y":50.262068},"pubMillis":1718527346000},{"uuid":"2a089389-fc27-48e6-833a-2771316ab13b","type":"POLICE","subtype":"POLICE_HIDING","location":{"x":18.727265,"y":50.262409},"pubMillis":1718527898000},{"uuid":"ade37393-c67a-40c2-b62e-95dbe7d9f914","type":"POLICE","subtype":"","location":{"x":18.913969,"y":50.283513},"pubMillis":1718527887000},{"uuid":"2938db90-41b7-4de9-952a-2918f1df6525","type":"POLICE","subtype":"","location":{"x":18.570614,"y":50.192113},"pubMillis":1718528476000},{"uuid":"a8cc13e9-5f80-4cc9-9401-2ce4aa0327ac","type":"POLICE","subtype":"","location":{"x":18.569761,"y":50.191562},"pubMillis":1718528486000},{"uuid":"05329b4f-9539-474d-a413-1447d2e3c132","type":"POLICE","subtype":"","location":{"x":19.030089,"y":50.263019},"pubMillis":1718528634000},{"uuid":"47969c79-5d97-4dad-9895-b88377912cca","type":"POLICE","subtype":"","location":{"x":19.443515,"y":50.072176},"pubMillis":1718530931000},{"uuid":"4996a471-1624-4f5e-91fd-ef52f50d4bfa","type":"POLICE","subtype":"POLICE_HIDING","location":{"x":18.857532,"y":50.257412},"pubMillis":1718531035000},{"uuid":"68f38f0b-5a72-4be3-9f00-fba1cf398592","type":"POLICE","subtype":"","location":{"x":19.021522,"y":50.32749},"pubMillis":1718531203000},{"uuid":"aa5836f0-853f-425a-a3f5-8a69c1c75a64","type":"POLICE","subtype":"","location":{"x":18.6866,"y":50.132482},"pubMillis":1718531363000},{"uuid":"1692952e-44c9-433a-90ec-314f65942bfd","type":"POLICE","subtype":"POLICE_HIDING","location":{"x":19.134128,"y":50.340435},"pubMillis":1718531631000},{"uuid":"2cb7df47-4617-41be-940e-65b07a0672c1","type":"POLICE","subtype":"","location":{"x":18.987839,"y":50.252145},"pubMillis":1718532461000},{"uuid":"4ed0d2ad-6af2-47e3-807c-5af03ce96449","type":"POLICE","subtype":"POLICE_HIDING","location":{"x":19.268933,"y":50.355112},"pubMillis":1718532588000},{"uuid":"d535319b-2366-4b17-8a29-93262349a3c3","type":"POLICE","subtype":"","location":{"x":19.445354,"y":50.071453},"pubMillis":1718533119000},{"uuid":"4d31707c-3130-4ab3-9ebc-b95684a753fc","type":"POLICE","subtype":"","location":{"x":19.008019,"y":50.273267},"pubMillis":1718533367000},{"uuid":"e4d5d370-e873-4647-88b1-426f95e9ec93","type":"POLICE","subtype":"","location":{"x":19.01872,"y":50.087086},"pubMillis":1718533962000},{"uuid":"ce9d65cd-3031-4ffa-bdc9-e2e77f6e9c88","type":"POLICE","subtype":"","location":{"x":19.433171,"y":50.074194},"pubMillis":1718534307000},{"uuid":"8a23108f-b265-4f63-a7ef-124c977222c7","type":"POLICE","subtype":"","location":{"x":19.326154,"y":50.020264},"pubMillis":1718534335000},{"uuid":"5f853e5a-5cb3-491a-ac71-854278c6c90f","type":"POLICE","subtype":"","location":{"x":19.327437,"y":50.020033},"pubMillis":1718534705000},{"uuid":"7dbfc6cb-8d2e-4640-8ba2-1baf640a35b6","type":"POLICE","subtype":"POLICE_HIDING","location":{"x":19.038557,"y":50.304902},"pubMillis":1718535725000},{"uuid":"f0987459-7ee3-4d87-ba3d-4011df14a0dd","type":"POLICE","subtype":"","location":{"x":18.702024,"y":50.281894},"pubMillis":1718536164000},{"uuid":"423ec2d5-f147-4bdc-a4b7-af17630c8cd7","type":"POLICE","subtype":"","location":{"x":18.98823,"y":50.110005},"pubMillis":1718538483000},{"uuid":"7096e38d-645d-428b-9168-ad5999dabe5c","type":"POLICE","subtype":"","location":{"x":18.941969,"y":50.200923},"pubMillis":1718539039000},{"uuid":"73605fc5-2bd7-4dbf-9124-05ed47231bde","type":"POLICE","subtype":"","location":{"x":18.595212,"y":50.328438},"pubMillis":1718539340000},{"uuid":"bf8e34c4-2383-4095-b834-7ecd9c09153a","type":"POLICE","subtype":"","location":{"x":19.09169,"y":50.253403},"pubMillis":1718539553000},{"uuid":"a1e0597d-ce12-4caa-864c-80e0b0f8bf93","type":"POLICE","subtype":"","location":{"x":19.351748,"y":50.016017},"pubMillis":1718540561000},{"uuid":"51a71e3d-3a0e-45dc-9735-b211e8e70fbc","type":"POLICE","subtype":"","location":{"x":19.059557,"y":50.216418},"pubMillis":1718540495000},{"uuid":"dc17bbb8-ddb3-4da0-8731-c5c127ea9567","type":"POLICE","subtype":"POLICE_HIDING","location":{"x":19.091533,"y":50.253268},"pubMillis":1718540667000},{"uuid":"9a74105a-a253-4675-85f7-d0f1d99070ea","type":"POLICE","subtype":"","location":{"x":19.059777,"y":50.216495},"pubMillis":1718540938000},{"uuid":"54d0a4b2-6c94-4903-bb69-2848f6942308","type":"POLICE","subtype":"POLICE_HIDING","location":{"x":18.870392,"y":50.301055},"pubMillis":1718541752000},{"uuid":"ce6d59ca-9f05-45dd-995e-9fb49b75badc","type":"POLICE","subtype":"","location":{"x":19.327027,"y":50.020109},"pubMillis":1718542676000},{"uuid":"2112a4da-1b9b-4ea0-9dae-6e976bdd39dc","type":"POLICE","subtype":"POLICE_HIDING","location":{"x":19.326947,"y":50.020121},"pubMillis":1718542735000},{"uuid":"4b7e48b0-18b6-4a69-8b22-5c1d0bde63c3","type":"POLICE","subtype":"","location":{"x":19.247383,"y":50.371902},"pubMillis":1718543027000},{"uuid":"e98faf74-0dbd-4724-aea6-6f16ebf42162","type":"POLICE","subtype":"","location":{"x":19.247758,"y":50.371214},"pubMillis":1718542992000},{"uuid":"62eb12b2-79f1-483c-9355-bc11ff8af4ea","type":"POLICE","subtype":"POLICE_HIDING","location":{"x":18.915686,"y":50.283565},"pubMillis":1718543598000},{"uuid":"5deafeb4-1902-4e0a-ad3d-31f847aa9832","type":"POLICE","subtype":"","location":{"x":19.0489,"y":50.264679},"pubMillis":1718543811000},{"uuid":"88dcd336-541f-40f2-8f6e-2153ee9f8bd7","type":"POLICE","subtype":"","location":{"x":19.247565,"y":50.371443},"pubMillis":1718544122000},{"uuid":"99f3fcd0-3188-416d-868c-fa32dce26b0f","type":"POLICE","subtype":"","location":{"x":18.79793,"y":50.264834},"pubMillis":1718544227000},{"uuid":"22dfc4c1-e88d-402c-9d51-6a19994fdff3","type":"POLICE","subtype":"","location":{"x":19.008178,"y":50.109901},"pubMillis":1718544411000},{"uuid":"8e4b5ba3-3181-48c4-8027-502cf58eb2e0","type":"POLICE","subtype":"","location":{"x":18.774521,"y":50.315069},"pubMillis":1718546329000},{"uuid":"810a09bf-39e0-4623-9096-6359a4ef6454","type":"POLICE","subtype":"","location":{"x":19.253414,"y":50.037982},"pubMillis":1718546525000},{"uuid":"7bd2a242-6b8d-456c-b165-ebfebfd8eea7","type":"POLICE","subtype":"POLICE_HIDING","location":{"x":18.884232,"y":50.306219},"pubMillis":1718546727000},{"uuid":"8f57dd9c-d9b8-4cf5-b004-dff1ba503523","type":"POLICE","subtype":"","location":{"x":19.017212,"y":50.329528},"pubMillis":1718546912000},{"uuid":"a8bad0b9-88c2-4273-80d5-12e9cf540a95","type":"POLICE","subtype":"","location":{"x":19.323794,"y":50.02046},"pubMillis":1718546889000},{"uuid":"bb2d3736-d1b4-43be-a823-bd417894ae11","type":"POLICE","subtype":"","location":{"x":18.695444,"y":50.282255},"pubMillis":1718546970000},{"uuid":"5b9c4692-1419-40af-8ab2-0b3d2c0a58d4","type":"POLICE","subtype":"","location":{"x":18.797097,"y":50.264802},"pubMillis":1718547915000},{"uuid":"f8c638fb-3532-426c-bd37-870d8aa8ee25","type":"POLICE","subtype":"","location":{"x":18.894527,"y":50.274806},"pubMillis":1718548061000},{"uuid":"8e537fdf-3c46-42fb-b48b-9c1b833b661a","type":"POLICE","subtype":"","location":{"x":19.059874,"y":50.216659},"pubMillis":1718548185000},{"uuid":"14c7c541-9448-434c-affc-944d12e3e7cc","type":"POLICE","subtype":"","location":{"x":19.375159,"y":50.303708},"pubMillis":1718548596000},{"uuid":"559dbd74-1bf4-4b0b-bf02-6e6ba0e43eba","type":"POLICE","subtype":"POLICE_HIDING","location":{"x":18.73183,"y":50.256168},"pubMillis":1718548904000},{"uuid":"bdce1d42-037c-4978-898b-35bae8b777ce","type":"POLICE","subtype":"","location":{"x":19.029846,"y":50.306295},"pubMillis":1718549290000},{"uuid":"137c13fb-0704-4a83-b8d2-0addaf5ab6bf","type":"POLICE","subtype":"","location":{"x":18.996175,"y":50.270715},"pubMillis":1718549461000},{"uuid":"c1182c2f-3fe9-427c-bac4-b9e44042efc9","type":"POLICE","subtype":"","location":{"x":19.058812,"y":50.22311},"pubMillis":1718549731000},{"uuid":"af802f80-94dd-4f3f-b486-f6f083383ff4","type":"POLICE","subtype":"","location":{"x":19.044319,"y":50.262243},"pubMillis":1718549953000},{"uuid":"da7ea888-7b67-4abe-aa41-0272d5830093","type":"POLICE","subtype":"","location":{"x":18.736808,"y":50.218792},"pubMillis":1718550499000},{"uuid":"bc7ff439-b403-4986-a66f-4a574e730e94","type":"POLICE","subtype":"","location":{"x":19.248015,"y":50.371151},"pubMillis":1718550718000},{"uuid":"cd82c016-9f7a-47c0-90ea-9c1a3a4dbbc3","type":"POLICE","subtype":"","location":{"x":19.059928,"y":50.217174},"pubMillis":1718550925000},{"uuid":"42806558-df60-48e6-97a9-f836c03a1600","type":"POLICE","subtype":"","location":{"x":18.939428,"y":50.333789},"pubMillis":1718550776000},{"uuid":"72a75d7f-b87d-4b93-98ac-35c88448b731","type":"POLICE","subtype":"","location":{"x":18.939732,"y":50.333313},"pubMillis":1718550817000},{"uuid":"99e68baa-bcc8-49b4-99b7-5615dde4d31d","type":"POLICE","subtype":"","location":{"x":18.581073,"y":50.214181},"pubMillis":1718551797000},{"uuid":"2f1cc8ad-9a93-4cfb-ae5c-3c88c887f9a4","type":"POLICE","subtype":"","location":{"x":19.117704,"y":50.24894},"pubMillis":1718551847000},{"uuid":"c8811238-3c11-403c-b307-b26bfb86710f","type":"POLICE","subtype":"","location":{"x":19.122892,"y":50.247769},"pubMillis":1718552474000},{"uuid":"6b46794f-93ff-470b-a466-7e4049be9ac9","type":"POLICE","subtype":"","location":{"x":19.012553,"y":50.124133},"pubMillis":1718552686000},{"uuid":"baf2ebed-112c-4dde-8ab4-77401b0adcfe","type":"POLICE","subtype":"","location":{"x":19.119646,"y":50.24847},"pubMillis":1718552763000},{"uuid":"0e837692-03f8-40c7-a7f2-ce9422e02f7c","type":"POLICE","subtype":"","location":{"x":18.829059,"y":50.275513},"pubMillis":1718552645000},{"uuid":"70f185c5-f200-4f41-9616-ff724f96097c","type":"POLICE","subtype":"","location":{"x":19.20883,"y":50.302661},"pubMillis":1718552610000},{"uuid":"a48886aa-aa14-48ff-96b7-ad9d90523499","type":"POLICE","subtype":"POLICE_HIDING","location":{"x":19.002148,"y":50.272884},"pubMillis":1718552932000},{"uuid":"252249de-f4dc-4d2e-935e-15cb24534906","type":"POLICE","subtype":"POLICE_HIDING","location":{"x":18.788606,"y":50.238358},"pubMillis":1718553216000},{"uuid":"8eb40033-b3ab-451d-be6f-40362af9246a","type":"POLICE","subtype":"POLICE_HIDING","location":{"x":19.137441,"y":50.300784},"pubMillis":1718553268000},{"uuid":"181dbbc0-5556-4f91-baa3-c3e31b8a2c5b","type":"POLICE","subtype":"","location":{"x":19.327558,"y":50.020009},"pubMillis":1718553360000},{"uuid":"5ad6dc63-a27f-4704-b867-c3a222690af5","type":"POLICE","subtype":"","location":{"x":18.788733,"y":50.237529},"pubMillis":1718553403000},{"uuid":"1fdb5772-b9cd-416d-8803-f6169d6c654a","type":"POLICE","subtype":"","location":{"x":18.855543,"y":50.288329},"pubMillis":1718553790000},{"uuid":"f11de6cd-b607-449f-9512-34e3db63a857","type":"POLICE","subtype":"","location":{"x":18.788697,"y":50.237768},"pubMillis":1718555922000},{"uuid":"ed265ffc-73fe-49f0-913f-3d66a0461439","type":"POLICE","subtype":"","location":{"x":18.946581,"y":50.317283},"pubMillis":1718556276000},{"uuid":"90e25646-f9c5-4227-a35a-efa03dc24adc","type":"POLICE","subtype":"","location":{"x":18.805327,"y":50.39915},"pubMillis":1718556076000},{"uuid":"74d01d37-d093-4a44-b651-591da7ed9362","type":"POLICE","subtype":"POLICE_HIDING","location":{"x":18.67616,"y":50.25886},"pubMillis":1718556775000},{"uuid":"0e5e4ad5-49e0-42cf-92ea-067ac4fec258","type":"POLICE","subtype":"","location":{"x":19.109633,"y":50.189846},"pubMillis":1718557000000},{"uuid":"e8adcfd4-9f54-4700-9a91-d1d588f36f18","type":"POLICE","subtype":"","location":{"x":19.247125,"y":50.372212},"pubMillis":1718557036000},{"uuid":"2227690e-0b26-477f-b29c-9448ab56aa06","type":"POLICE","subtype":"","location":{"x":19.109394,"y":50.18985},"pubMillis":1718557145000},{"uuid":"3b7e96ac-c3b5-4392-93bd-88aaf8971db8","type":"POLICE","subtype":"POLICE_VISIBLE","location":{"x":19.015865,"y":50.329788},"pubMillis":1718557283000},{"uuid":"82790118-564c-4ea3-8516-c500fc3cf353","type":"POLICE","subtype":"","location":{"x":19.137208,"y":50.30077},"pubMillis":1718557283000},{"uuid":"001910f6-632e-4a6e-90ee-b8f5c2f9d4b6","type":"POLICE","subtype":"","location":{"x":19.247068,"y":50.372033},"pubMillis":1718557242000},{"uuid":"f77baf7d-c717-4584-915f-1357aa16f0e9","type":"POLICE","subtype":"POLICE_HIDING","location":{"x":18.946089,"y":50.342286},"pubMillis":1718557387000},{"uuid":"1cc50da4-b29f-495c-a058-e7c116b2e534","type":"POLICE","subtype":"POLICE_HIDING","location":{"x":19.131594,"y":50.083817},"pubMillis":1718558397000},{"uuid":"39424c78-36ea-4ea7-84b2-276fb8c4c07e","type":"POLICE","subtype":"POLICE_HIDING","location":{"x":18.789182,"y":50.234452},"pubMillis":1718558505000},{"uuid":"a421ed05-d86b-4791-a82b-f6e5a9531740","type":"POLICE","subtype":"","location":{"x":19.246926,"y":50.372202},"pubMillis":1718559007000},{"uuid":"74ea0c30-0309-4394-8759-c20aee144a86","type":"POLICE","subtype":"","location":{"x":19.018712,"y":50.087075},"pubMillis":1718559298000},{"uuid":"85cc17e8-e075-4341-bc46-ca4f03d0e767","type":"POLICE","subtype":"","location":{"x":18.891258,"y":50.324198},"pubMillis":1718559708000},{"uuid":"53a93d6b-6d90-43f3-b943-1befb20432a5","type":"POLICE","subtype":"","location":{"x":19.120061,"y":50.297962},"pubMillis":1718560314000},{"uuid":"11298747-bba6-41d7-b98a-87d0faa872d0","type":"POLICE","subtype":"","location":{"x":19.017349,"y":50.329501},"pubMillis":1718561264000},{"uuid":"82d2d0f4-9544-4117-9a67-ff5410e1fdff","type":"POLICE","subtype":"","location":{"x":19.247551,"y":50.37146},"pubMillis":1718561669000},{"uuid":"f9231142-7a94-4a2d-9593-18eb12f249bd","type":"POLICE","subtype":"","location":{"x":19.246614,"y":50.372821},"pubMillis":1718562828000},{"uuid":"96df1ede-2a01-48c9-a958-43ef39734c50","type":"POLICE","subtype":"","location":{"x":19.016533,"y":50.329659},"pubMillis":1718563668000},{"uuid":"b1b18f96-db2d-4bb4-8d89-b48e7d13a1e0","type":"POLICE","subtype":"","location":{"x":19.253412,"y":50.038074},"pubMillis":1718564113000},{"uuid":"4114bbe5-b076-4d99-9339-b043d7d35ec1","type":"POLICE","subtype":"POLICE_HIDING","location":{"x":18.73317,"y":50.267713},"pubMillis":1718564639000},{"uuid":"aa8dd722-08dc-4226-8ae0-e38f427a8086","type":"POLICE","subtype":"","location":{"x":18.940829,"y":50.253808},"pubMillis":1718565745000},{"uuid":"99ba81d9-58be-484c-ba96-505c165a459f","type":"POLICE","subtype":"POLICE_HIDING","location":{"x":18.993394,"y":50.205995},"pubMillis":1718566281000},{"uuid":"d68813e3-7f7c-4d8f-a923-e2f07b6093a9","type":"POLICE","subtype":"POLICE_HIDING","location":{"x":18.939709,"y":50.253634},"pubMillis":1718566357000},{"uuid":"1bda3136-4d4f-41fd-8cca-f2e4dc236f38","type":"POLICE","subtype":"POLICE_HIDING","location":{"x":19.242321,"y":50.225187},"pubMillis":1718567194000},{"uuid":"f315087c-1e7c-4795-9b1a-8c00d98dbe2b","type":"POLICE","subtype":"","location":{"x":19.145242,"y":50.301329},"pubMillis":1718569867000},{"uuid":"8f8fa4c3-141d-430b-922b-f076b95b80b6","type":"POLICE","subtype":"","location":{"x":18.674279,"y":50.25885},"pubMillis":1718571005000},{"uuid":"62eb70dd-5d8e-4da7-9670-e389f0c195b7","type":"POLICE","subtype":"","location":{"x":18.867587,"y":50.419065},"pubMillis":1718571399000},{"uuid":"5a033369-b8c5-4efc-b2ae-e27f1b337fd9","type":"POLICE","subtype":"","location":{"x":19.110514,"y":50.280124},"pubMillis":1718572103000},{"uuid":"cb7c9926-8b99-4b3f-b609-2a38f0758878","type":"POLICE","subtype":"","location":{"x":19.043242,"y":50.24795},"pubMillis":1718572188000},{"uuid":"3744c313-6d04-4fdd-af71-26bd9af0bd3e","type":"POLICE","subtype":"","location":{"x":19.041978,"y":50.248877},"pubMillis":1718572212000},{"uuid":"76154e58-6c43-4aef-8ef5-ba763d124b6e","type":"POLICE","subtype":"","location":{"x":18.901999,"y":50.399131},"pubMillis":1718572524000},{"uuid":"82a90658-684c-4727-8b7d-805c727f03f2","type":"POLICE","subtype":"","location":{"x":19.01717,"y":50.254148},"pubMillis":1718573445000},{"uuid":"3bd94c21-5cb9-43d9-a5c6-584efedfc209","type":"POLICE","subtype":"","location":{"x":19.020523,"y":50.257745},"pubMillis":1718573333000},{"uuid":"241172a7-856e-4075-aedc-902ed142fd01","type":"POLICE","subtype":"","location":{"x":19.484007,"y":50.483906},"pubMillis":1718573397000},{"uuid":"f0fb5728-538a-4514-8ad2-a7468e7c29e3","type":"POLICE","subtype":"","location":{"x":19.168796,"y":50.078797},"pubMillis":1718573474000},{"uuid":"0cc35c00-fe63-4e65-975d-a66dc07ce4f9","type":"POLICE","subtype":"","location":{"x":18.982214,"y":50.252128},"pubMillis":1718574698000},{"uuid":"437bad1f-8b26-41de-8dd2-b3cd9e82e457","type":"POLICE","subtype":"","location":{"x":18.6747,"y":50.258852},"pubMillis":1718581575000},{"uuid":"1a1fd1c9-4453-4c50-bafc-be87af483290","type":"POLICE","subtype":"","location":{"x":19.013822,"y":50.163454},"pubMillis":1718582651000},{"uuid":"6be46237-0b55-46f2-8c4e-27f0b99baddc","type":"POLICE","subtype":"POLICE_HIDING","location":{"x":18.98218,"y":50.252398},"pubMillis":1718583744000},{"uuid":"a09de558-429e-4c1c-b1d1-3141d6796ec5","type":"POLICE","subtype":"","location":{"x":18.677307,"y":50.259647},"pubMillis":1718585946000},{"uuid":"60aa5e23-d1f4-4fa0-aa4f-69e60f579433","type":"POLICE","subtype":"","location":{"x":18.934902,"y":50.252842},"pubMillis":1718586403000},{"uuid":"39fb0a97-c16d-456c-b78b-5d8672b69c86","type":"POLICE","subtype":"","location":{"x":19.058688,"y":50.215347},"pubMillis":1718586829000},{"uuid":"dc934372-4565-43a0-b0e7-0eeeaaf9df0a","type":"POLICE","subtype":"","location":{"x":18.884345,"y":50.306539},"pubMillis":1718590093000},{"uuid":"b47b2486-2381-4f65-86a7-fa3a78f7271e","type":"POLICE","subtype":"","location":{"x":19.056357,"y":50.212679},"pubMillis":1718592591000},{"uuid":"246982cf-6028-49c5-b22d-45240ba13c6c","type":"POLICE","subtype":"","location":{"x":19.060101,"y":50.217761},"pubMillis":1718593255000},{"uuid":"04560f44-8b9b-4760-9a26-17f25f1d7810","type":"POLICE","subtype":"","location":{"x":18.857043,"y":50.320998},"pubMillis":1718594693000},{"uuid":"0a1bc5f1-8433-460b-a1db-2132cf6e2aab","type":"POLICE","subtype":"","location":{"x":19.083993,"y":50.107291},"pubMillis":1718595623000},{"uuid":"c9af60e4-02fc-42ec-9688-58a26e89b950","type":"POLICE","subtype":"","location":{"x":19.059535,"y":50.216096},"pubMillis":1718595639000},{"uuid":"5092160b-0ea2-4995-9bc4-925374bba1b4","type":"POLICE","subtype":"","location":{"x":19.147935,"y":50.241987},"pubMillis":1718596285000},{"uuid":"41808a04-964c-4793-bf72-4e70fe32bc2d","type":"POLICE","subtype":"","location":{"x":19.073948,"y":50.265073},"pubMillis":1718598535000},{"uuid":"25397158-6d70-425b-954b-b5f5e156fb0e","type":"POLICE","subtype":"","location":{"x":19.117395,"y":50.249015},"pubMillis":1718598970000},{"uuid":"9105905b-42d8-4bd4-8a13-1e8e30463ba4","type":"POLICE","subtype":"","location":{"x":19.066712,"y":50.232055},"pubMillis":1718600376000},{"uuid":"b08f7e77-f9ff-4fd2-a113-ea9838000ac2","type":"POLICE","subtype":"","location":{"x":18.965746,"y":50.288708},"pubMillis":1718600839000},{"uuid":"d94aa4b4-c1f9-487a-8b96-7ec77632b484","type":"POLICE","subtype":"","location":{"x":18.979739,"y":50.279648},"pubMillis":1718600956000},{"uuid":"ec340393-bc26-4571-8d09-d05e14a50cc4","type":"POLICE","subtype":"","location":{"x":18.828692,"y":50.31956},"pubMillis":1718601544000},{"uuid":"2356768b-8d4f-4673-90dc-f2917f6152a1","type":"POLICE","subtype":"","location":{"x":19.023642,"y":50.125996},"pubMillis":1718601732000},{"uuid":"2a85087b-820b-4788-9b38-007d404c0613","type":"POLICE","subtype":"","location":{"x":18.985838,"y":50.260043},"pubMillis":1718601838000},{"uuid":"f48fa9a0-815d-4549-b57a-ae0a7f9de9be","type":"POLICE","subtype":"","location":{"x":19.29371,"y":50.203779},"pubMillis":1718601950000},{"uuid":"1638e30e-bc9e-4e6d-9c78-8f517d847115","type":"POLICE","subtype":"","location":{"x":19.019242,"y":50.329112},"pubMillis":1718602332000},{"uuid":"b1fd6eeb-4e69-432d-841a-3114b0ba6817","type":"POLICE","subtype":"","location":{"x":18.884899,"y":50.3031},"pubMillis":1718602403000},{"uuid":"667ad79c-7454-4ba7-9cb8-774aef12a777","type":"POLICE","subtype":"","location":{"x":19.029235,"y":50.227292},"pubMillis":1718602513000},{"uuid":"b0b03ed6-c95e-4015-8375-090ed3f2dc7c","type":"POLICE","subtype":"POLICE_HIDING","location":{"x":19.229509,"y":50.170768},"pubMillis":1718602883000},{"uuid":"2a619e65-acfe-40eb-857c-b8beab44740e","type":"POLICE","subtype":"POLICE_HIDING","location":{"x":19.011633,"y":50.177825},"pubMillis":1718603113000},{"uuid":"650c7e7a-cac0-443a-a627-85a6587a6ad6","type":"POLICE","subtype":"","location":{"x":19.059305,"y":50.453544},"pubMillis":1718603709000},{"uuid":"98e90184-a147-4ae7-90c6-a72049c2900b","type":"POLICE","subtype":"POLICE_HIDING","location":{"x":19.137799,"y":50.300714},"pubMillis":1718603758000},{"uuid":"0af1d569-e37d-4903-919a-ac6bc7b4092b","type":"POLICE","subtype":"","location":{"x":18.712453,"y":50.16857},"pubMillis":1718603849000},{"uuid":"308dcb28-cf5c-4095-8058-48e238276795","type":"POLICE","subtype":"","location":{"x":18.732557,"y":50.255763},"pubMillis":1718603973000},{"uuid":"9c293ecd-c958-47b5-a032-11c2b5229897","type":"POLICE","subtype":"","location":{"x":19.024515,"y":50.128242},"pubMillis":1718604105000},{"uuid":"7851bc94-f87d-492c-b767-f3d6e48ec440","type":"POLICE","subtype":"","location":{"x":19.005661,"y":50.179654},"pubMillis":1718604536000}]